ds9samp/__init__.py
ds9samp/scripts.py
ds9samp-0.1.1.dist-info/METADATA
ds9samp-0.1.1.dist-info/WHEEL
ds9samp-0.1.1.dist-info/entry_points.txt
ds9samp-0.1.1.dist-info/licenses/LICENSE
ds9samp-0.1.1.dist-info/RECORD
