Metadata-Version: 2.4
Name: ds9samp
Version: 0.1.1
Summary: Control SAOImageDS9 from Python
Project-URL: Homepage, https://github.com/cxcsds/ds9samp
Project-URL: Issues, https://github.com/cxcsds/ds9samp/issues
Author-email: Douglas Burke <dburke@cfa.harvard.edu>
License-File: LICENSE
Classifier: Development Status :: 3 - Alpha
Classifier: Environment :: X11 Applications
Classifier: Intended Audience :: Science/Research
Classifier: License :: OSI Approved :: GNU General Public License v3 (GPLv3)
Classifier: Operating System :: POSIX
Classifier: Programming Language :: Python :: 3
Classifier: Topic :: Communications
Classifier: Topic :: Multimedia :: Graphics :: Viewers
Classifier: Topic :: Scientific/Engineering :: Astronomy
Requires-Python: >=3.10
Requires-Dist: astropy
Requires-Dist: numpy>=1.20
